crdf_serializer/__init__.py
crdf_serializer/bind_decorator.py
crdf_serializer/object_decorator.py
tests/__init__.py
tests/context.py
tests/test_example_rdflib.py
tests/test_graph_all.py
crdf_serializer-0.0.1.dist-info/LICENSE
crdf_serializer-0.0.1.dist-info/METADATA
crdf_serializer-0.0.1.dist-info/WHEEL
crdf_serializer-0.0.1.dist-info/top_level.txt
crdf_serializer-0.0.1.dist-info/RECORD
