Metadata-Version: 2.1
Name: crdf-serializer
Version: 0.0.1
Summary: Some decorators responsible for preparing and serializing RDF files.
Home-page: https://github.com/vittorduartte/crdf_serializer
Author: Prof. Sergio Costa
Author-email: prof.sergio.costa@gmail.com
License: UNKNOWN
Platform: UNKNOWN
Classifier: Programming Language :: Python :: 3
Classifier: License :: OSI Approved :: MIT License
Classifier: Operating System :: OS Independent
